wtss/__init__.py
wtss/cli.py
wtss/coverage.py
wtss/timeseries.py
wtss/utils.py
wtss/version.py
wtss/wtss.py
wtss/templates/coverage.html
wtss/templates/timeseries.html
wtss/templates/wtss.html
wtss-0.7.1.dist-info/LICENSE
wtss-0.7.1.dist-info/METADATA
wtss-0.7.1.dist-info/WHEEL
wtss-0.7.1.dist-info/entry_points.txt
wtss-0.7.1.dist-info/top_level.txt
wtss-0.7.1.dist-info/RECORD
