Metadata-Version: 2.1
Name: wtss
Version: 0.7.1
Summary: Python Client Library for WTSS.
Home-page: https://github.com/brazil-data-cube/wtss.py
Author: Brazil Data Cube Team
Author-email: brazildatacube@inpe.br
License: GPLv3
Keywords: Web Time Series Service,Time series,Earth Observations
Platform: any
Classifier: Development Status :: 3 - Alpha
Classifier: Environment :: Web Environment
Classifier: Intended Audience :: Education
Classifier: Intended Audience :: Science/Research
Classifier: License :: OSI Approved :: GNU General Public License v3 (GPLv3)
Classifier: Operating System :: OS Independent
Classifier: Programming Language :: Python :: 3.7
Classifier: Programming Language :: Python :: 3.8
Classifier: Programming Language :: Python :: 3.9
Classifier: Programming Language :: Python :: 3.10
Classifier: Programming Language :: Python :: 3.11
Classifier: Topic :: Software Development :: Libraries :: Python Modules
Classifier: Topic :: Scientific/Engineering :: GIS
License-File: LICENSE
Requires-Dist: Click >=7.0
Requires-Dist: jsonschema >=3.2
Requires-Dist: requests >=2.20
Requires-Dist: Jinja2 >=2.10
Provides-Extra: all
Requires-Dist: Sphinx >=2.2 ; extra == 'all'
Requires-Dist: sphinx-rtd-theme ; extra == 'all'
Requires-Dist: sphinx-copybutton ; extra == 'all'
Requires-Dist: matplotlib >=3.1 ; extra == 'all'
Requires-Dist: numpy >=1.18 ; extra == 'all'
Requires-Dist: coverage >=4.5 ; extra == 'all'
Requires-Dist: pytest >=5.2 ; extra == 'all'
Requires-Dist: pytest-cov >=2.8 ; extra == 'all'
Requires-Dist: pytest-pep8 >=1.0 ; extra == 'all'
Requires-Dist: pydocstyle >=4.0 ; extra == 'all'
Requires-Dist: isort >4.3 ; extra == 'all'
Requires-Dist: check-manifest >=0.40 ; extra == 'all'
Requires-Dist: numpy >=1.13 ; extra == 'all'
Requires-Dist: matplotlib >=2.1 ; extra == 'all'
Provides-Extra: docs
Requires-Dist: Sphinx >=2.2 ; extra == 'docs'
Requires-Dist: sphinx-rtd-theme ; extra == 'docs'
Requires-Dist: sphinx-copybutton ; extra == 'docs'
Provides-Extra: examples
Requires-Dist: matplotlib >=3.1 ; extra == 'examples'
Requires-Dist: numpy >=1.18 ; extra == 'examples'
Provides-Extra: matplotlib
Requires-Dist: numpy >=1.13 ; extra == 'matplotlib'
Requires-Dist: matplotlib >=2.1 ; extra == 'matplotlib'
Provides-Extra: tests
Requires-Dist: coverage >=4.5 ; extra == 'tests'
Requires-Dist: pytest >=5.2 ; extra == 'tests'
Requires-Dist: pytest-cov >=2.8 ; extra == 'tests'
Requires-Dist: pytest-pep8 >=1.0 ; extra == 'tests'
Requires-Dist: pydocstyle >=4.0 ; extra == 'tests'
Requires-Dist: isort >4.3 ; extra == 'tests'
Requires-Dist: check-manifest >=0.40 ; extra == 'tests'
